README.txt
setup.py
tengs_cli/__init__.py
tengs_cli/actions.py
tengs_cli/cli.py
tengs_cli/settings.py
tengs_cli.egg-info/PKG-INFO
tengs_cli.egg-info/SOURCES.txt
tengs_cli.egg-info/dependency_links.txt
tengs_cli.egg-info/entry_points.txt
tengs_cli.egg-info/requires.txt
tengs_cli.egg-info/top_level.txt
test/test_actions.py
test/test_cli.py