Metadata-Version: 1.0
Name: tengs-cli
Version: 0.0.9
Summary: cli for tengs.ru
Home-page: http://tengs.ru
Author: Kirill Mokevnin
Author-email: mokevnin@gmail.com
License: MIT
Platform: UNKNOWN
